SweeplineVT/SweeplineVT.py
SweeplineVT/__init__.py
SweeplineVT-0.0.8.data/scripts/pl_VT.py
SweeplineVT-0.0.8.data/scripts/slvt.py
SweeplineVT-0.0.8.dist-info/LICENSE
SweeplineVT-0.0.8.dist-info/METADATA
SweeplineVT-0.0.8.dist-info/WHEEL
SweeplineVT-0.0.8.dist-info/top_level.txt
SweeplineVT-0.0.8.dist-info/RECORD
