Metadata-Version: 2.1
Name: SweeplineVT
Version: 0.0.8
Summary: Voronoi Tessellation using Sweep-line algorithm
Home-page: https://github.com/lewtonstein/SweeplineVT
Author: Teng Liu
Author-email: lewtonstein@gmail.com
License: UNKNOWN
Platform: UNKNOWN
Classifier: Programming Language :: Python :: 3
Classifier: License :: OSI Approved :: GNU General Public License v3 (GPLv3)
Classifier: Operating System :: OS Independent
Requires-Python: >=3.6
Requires-Dist: numpy
Requires-Dist: astropy
Requires-Dist: matplotlib
